genai_4_dps_helper/__init__.py
genai_4_dps_helper/base_obj.py
genai_4_dps_helper/db2.py
genai_4_dps_helper/eu_law.py
genai_4_dps_helper/milvus.py
genai_4_dps_helper/text_extractors.py
genai_4_dps_helper/watsonx.py
genai_4_dps_helper/models/__init__.py
genai_4_dps_helper/models/generic_base_models.py
genai_4_dps_helper/utils/__init__.py
genai_4_dps_helper/utils/log_config.py
genai_4_dps_helper-0.2.32.dist-info/licenses/LICENSE
genai_4_dps_helper-0.2.32.dist-info/METADATA
genai_4_dps_helper-0.2.32.dist-info/WHEEL
genai_4_dps_helper-0.2.32.dist-info/top_level.txt
genai_4_dps_helper-0.2.32.dist-info/RECORD
