Metadata-Version: 2.4
Name: genai_4_dps_helper
Version: 0.2.32
Summary: A common library for reusable and repeated code for the GenAI4DPS Training Courses.
Author-email: "Benjamin A. Janes" <benjamin.janes@se.ibm.com>
Project-URL: Homepage, https://github.com/Nniol/genai_4_dps_helper
Project-URL: Issues, https://github.com/Nniol/genai_4_dps_helper/issues
Classifier: Programming Language :: Python :: 3
Classifier: License :: OSI Approved :: Apache Software License
Classifier: Operating System :: OS Independent
Requires-Python: >=3.11
License-File: LICENSE
Requires-Dist: ibm_watsonx_ai==1.3.34
Requires-Dist: pandas==2.2.3
Requires-Dist: pymilvus==2.6.0
Requires-Dist: pydantic==2.11.7
Requires-Dist: pypdf==6.0.0
Requires-Dist: ibm_db==3.2.6
Dynamic: license-file
